cpu_original/src/alu.v
module alu (
    input  wire [15:0] a,
    input  wire [15:0] b,
    input  wire [1:0]  alu_sel,   // 00=ADD,01=SUB,10=AND,11=NOP
    output reg  [15:0] result,
    output reg         zero,
    output reg         negative,
    output reg         carry
);
    reg [16:0] ext;
    always @(*) begin
        case (alu_sel)
            2'b00: begin // ADD
                ext = {1'b0, a} + {1'b0, b};
                result   = ext[15:0];
                carry    = ext[16];
                negative = result[15];
                zero     = (result == 16'b0);
            end
            2'b01: begin // SUB
                ext = {1'b0, a} - {1'b0, b};
                result   = ext[15:0];
                carry    = ext[16];
                negative = result[15];
                zero     = (result == 16'b0);
            end
            2'b10: begin // AND
                result   = a & b;
                carry    = 1'b0;
                negative = result[15];
                zero     = (result == 16'b0);
            end
            default: begin // NOP
                result   = 16'b0;
                carry    = 1'b0;
                negative = 1'b0;
                zero     = 1'b1;
            end
        endcase
    end
endmodule

cpu/test/alu_tb.v
`timescale 1ns/1ps

module alu_tb;
    // Testbench signals
    reg  [15:0] a, b;
    reg  [1:0]  alu_sel;
    wire [15:0] result;
    wire        zero, negative, carry;

    // Test tracking
    integer pass_count = 0;
    integer fail_count = 0;

    // Instantiate the ALU
    alu uut (
        .a(a),
        .b(b),
        .alu_sel(alu_sel),
        .result(result),
        .zero(zero),
        .negative(negative),
        .carry(carry)
    );

    // Task to check result and flags
    task check;
        input [15:0] exp_result;
        input        exp_zero;
        input        exp_negative;
        input        exp_carry;
        input [63:0] test_name; // 8-char test name
        begin
            #1; // Allow combinational logic to settle
            if (result === exp_result && zero === exp_zero && 
                negative === exp_negative && carry === exp_carry) begin
                $display("PASS: %s | a=%h b=%h sel=%b => result=%h z=%b n=%b c=%b",
                         test_name, a, b, alu_sel, result, zero, negative, carry);
                pass_count = pass_count + 1;
            end else begin
                $display("FAIL: %s | a=%h b=%h sel=%b", test_name, a, b, alu_sel);
                $display("      Expected: result=%h z=%b n=%b c=%b", 
                         exp_result, exp_zero, exp_negative, exp_carry);
                $display("      Got:      result=%h z=%b n=%b c=%b", 
                         result, zero, negative, carry);
                fail_count = fail_count + 1;
            end
        end
    endtask

    initial begin
        // Setup waveform dump
        $dumpfile("test/alu_tb.vcd");
        $dumpvars(0, alu_tb);

        $display("========================================");
        $display("         ALU Testbench Start");
        $display("========================================");

        // ----------------------------------------
        // ADD Tests (alu_sel = 2'b00)
        // ----------------------------------------
        $display("\n--- ADD Tests ---");
        alu_sel = 2'b00;

        // Basic addition: 5 + 3 = 8
        a = 16'h0005; b = 16'h0003;
        check(16'h0008, 1'b0, 1'b0, 1'b0, "ADD_BASIC");

        // Zero result: 0 + 0 = 0
        a = 16'h0000; b = 16'h0000;
        check(16'h0000, 1'b1, 1'b0, 1'b0, "ADD_ZERO");

        // Carry/overflow: FFFF + 1 = 0 (with carry)
        a = 16'hFFFF; b = 16'h0001;
        check(16'h0000, 1'b1, 1'b0, 1'b1, "ADD_CARRY");

        // Carry with non-zero result: FFFF + 2 = 1 (with carry)
        a = 16'hFFFF; b = 16'h0002;
        check(16'h0001, 1'b0, 1'b0, 1'b1, "ADD_CAR2");

        // Negative result: 0x7FFF + 1 = 0x8000 (MSB set)
        a = 16'h7FFF; b = 16'h0001;
        check(16'h8000, 1'b0, 1'b1, 1'b0, "ADD_NEG");

        // Large addition no carry: 0x8000 + 0x7FFF = 0xFFFF
        a = 16'h8000; b = 16'h7FFF;
        check(16'hFFFF, 1'b0, 1'b1, 1'b0, "ADD_LARG");

        // ----------------------------------------
        // SUB Tests (alu_sel = 2'b01)
        // ----------------------------------------
        $display("\n--- SUB Tests ---");
        alu_sel = 2'b01;

        // Basic subtraction: 8 - 3 = 5
        a = 16'h0008; b = 16'h0003;
        check(16'h0005, 1'b0, 1'b0, 1'b0, "SUB_BASIC");

        // Zero result: 5 - 5 = 0
        a = 16'h0005; b = 16'h0005;
        check(16'h0000, 1'b1, 1'b0, 1'b0, "SUB_ZERO");

        // Borrow/underflow: 0 - 1 = FFFF (with borrow)
        a = 16'h0000; b = 16'h0001;
        check(16'hFFFF, 1'b0, 1'b1, 1'b1, "SUB_BORW");

        // Borrow: 5 - 10 = FFFB (with borrow)
        a = 16'h0005; b = 16'h000A;
        check(16'hFFFB, 1'b0, 1'b1, 1'b1, "SUB_BOR2");

        // No borrow, negative result: 0x8000 - 1 = 0x7FFF
        a = 16'h8000; b = 16'h0001;
        check(16'h7FFF, 1'b0, 1'b0, 1'b0, "SUB_NOBO");

        // Large subtraction: 0xFFFF - 0xFFFF = 0
        a = 16'hFFFF; b = 16'hFFFF;
        check(16'h0000, 1'b1, 1'b0, 1'b0, "SUB_LARG");

        // ----------------------------------------
        // AND Tests (alu_sel = 2'b10)
        // ----------------------------------------
        $display("\n--- AND Tests ---");
        alu_sel = 2'b10;

        // Basic AND: 0xFF00 & 0x0FF0 = 0x0F00
        a = 16'hFF00; b = 16'h0FF0;
        check(16'h0F00, 1'b0, 1'b0, 1'b0, "AND_BASIC");

        // Zero result: 0xAAAA & 0x5555 = 0x0000
        a = 16'hAAAA; b = 16'h5555;
        check(16'h0000, 1'b1, 1'b0, 1'b0, "AND_ZERO");

        // All ones: 0xFFFF & 0xFFFF = 0xFFFF
        a = 16'hFFFF; b = 16'hFFFF;
        check(16'hFFFF, 1'b0, 1'b1, 1'b0, "AND_ONES");

        // Negative result: 0x8000 & 0xFFFF = 0x8000
        a = 16'h8000; b = 16'hFFFF;
        check(16'h8000, 1'b0, 1'b1, 1'b0, "AND_NEG");

        // Partial mask: 0x1234 & 0x00FF = 0x0034
        a = 16'h1234; b = 16'h00FF;
        check(16'h0034, 1'b0, 1'b0, 1'b0, "AND_MASK");

        // ----------------------------------------
        // NOP Tests (alu_sel = 2'b11)
        // ----------------------------------------
        $display("\n--- NOP Tests ---");
        alu_sel = 2'b11;

        // NOP with random inputs: should output 0
        a = 16'h1234; b = 16'h5678;
        check(16'h0000, 1'b1, 1'b0, 1'b0, "NOP_RND");

        // NOP with all ones: should still output 0
        a = 16'hFFFF; b = 16'hFFFF;
        check(16'h0000, 1'b1, 1'b0, 1'b0, "NOP_ONES");

        // NOP with zeros
        a = 16'h0000; b = 16'h0000;
        check(16'h0000, 1'b1, 1'b0, 1'b0, "NOP_ZERO");

        // ----------------------------------------
        // Summary
        // ----------------------------------------
        $display("\n========================================");
        $display("         ALU Testbench Complete");
        $display("========================================");
        $display("Passed: %0d", pass_count);
        $display("Failed: %0d", fail_count);
        if (fail_count == 0)
            $display("ALL TESTS PASSED!");
        else
            $display("SOME TESTS FAILED!");
        $display("========================================\n");

        $finish;
    end

endmodule

cpu/test/alu_tb.vcd
$date
	Mon Jan  5 20:58:40 2026
$end
$version
	Icarus Verilog
$end
$timescale
	1ps
$end
$scope module alu_tb $end
$var wire 1 ! zero $end
$var wire 16 " result [15:0] $end
$var wire 1 # negative $end
$var wire 1 $ carry $end
$var reg 16 % a [15:0] $end
$var reg 2 & alu_sel [1:0] $end
$var reg 16 ' b [15:0] $end
$var integer 32 ( fail_count [31:0] $end
$var integer 32 ) pass_count [31:0] $end
$scope module uut $end
$var wire 16 * a [15:0] $end
$var wire 2 + alu_sel [1:0] $end
$var wire 16 , b [15:0] $end
$var reg 1 $ carry $end
$var reg 17 - ext [16:0] $end
$var reg 1 # negative $end
$var reg 16 . result [15:0] $end
$var reg 1 ! zero $end
$upscope $end
$scope task check $end
$var reg 1 / exp_carry $end
$var reg 1 0 exp_negative $end
$var reg 16 1 exp_result [15:0] $end
$var reg 1 2 exp_zero $end
$var reg 64 3 test_name [63:0] $end
$upscope $end
$upscope $end
$enddefinitions $end
$comment Show the parameter values. $end
$dumpall
$end
#0
$dumpvars
b100010001000100010111110100001001000001010100110100100101000011 3
02
b1000 1
00
0/
b1000 .
b1000 -
b11 ,
b0 +
b101 *
b0 )
b0 (
b11 '
b0 &
b101 %
0$
0#
b1000 "
0!
$end
#1000
1!
b0 "
b0 .
b0 -
b100000101000100010001000101111101011010010001010101001001001111 3
12
b0 1
b0 '
b0 ,
b0 %
b0 *
b1 )
#2000
1$
b10000000000000000 -
b100010001000100010111110100001101000001010100100101001001011001 3
1/
b1 '
b1 ,
b1111111111111111 %
b1111111111111111 *
b10 )
#3000
0!
b1 "
b1 .
b10000000000000001 -
b100000101000100010001000101111101000011010000010101001000110010 3
02
b1 1
b10 '
b10 ,
b11 )
#4000
1#
0$
b1000000000000000 "
b1000000000000000 .
b1000000000000000 -
b1000001010001000100010001011111010011100100010101000111 3
0/
10
b1000000000000000 1
b1 '
b1 ,
b111111111111111 %
b111111111111111 *
b100 )
#5000
b1111111111111111 "
b1111111111111111 .
b1111111111111111 -
b100000101000100010001000101111101001100010000010101001001000111 3
b1111111111111111 1
b111111111111111 '
b111111111111111 ,
b1000000000000000 %
b1000000000000000 *
b101 )
#6000
0#
b101 "
b101 .
b101 -
b101010101000010010111110100001001000001010100110100100101000011 3
00
b101 1
b11 '
b11 ,
b1000 %
b1000 *
b1 &
b1 +
b110 )
#7000
1!
b0 "
b0 .
b0 -
b101001101010101010000100101111101011010010001010101001001001111 3
12
b0 1
b101 '
b101 ,
b101 %
b101 *
b111 )
#8000
0!
1#
1$
b1111111111111111 "
b1111111111111111 .
b11111111111111111 -
b101001101010101010000100101111101000010010011110101001001010111 3
1/
10
02
b1111111111111111 1
b1 '
b1 ,
b0 %
b0 *
b1000 )
#9000
b1111111111111011 "
b1111111111111011 .
b11111111111111011 -
b101001101010101010000100101111101000010010011110101001000110010 3
b1111111111111011 1
b1010 '
b1010 ,
b101 %
b101 *
b1001 )
#10000
0#
0$
b111111111111111 "
b111111111111111 .
b111111111111111 -
b101001101010101010000100101111101001110010011110100001001001111 3
0/
00
b111111111111111 1
b1 '
b1 ,
b1000000000000000 %
b1000000000000000 *
b1010 )
#11000
1!
b0 "
b0 .
b0 -
b101001101010101010000100101111101001100010000010101001001000111 3
12
b0 1
b1111111111111111 '
b1111111111111111 ,
b1111111111111111 %
b1111111111111111 *
b1011 )
#12000
0!
b111100000000 "
b111100000000 .
b100111001000100010111110100001001000001010100110100100101000011 3
02
b111100000000 1
b111111110000 '
b111111110000 ,
b1111111100000000 %
b1111111100000000 *
b10 &
b10 +
b1100 )
#13000
1!
b0 "
b0 .
b100000101001110010001000101111101011010010001010101001001001111 3
12
b0 1
b101010101010101 '
b101010101010101 ,
b1010101010101010 %
b1010101010101010 *
b1101 )
#14000
0!
1#
b1111111111111111 "
b1111111111111111 .
b100000101001110010001000101111101001111010011100100010101010011 3
10
02
b1111111111111111 1
b1111111111111111 '
b1111111111111111 ,
b1111111111111111 %
b1111111111111111 *
b1110 )
#15000
b1000000000000000 "
b1000000000000000 .
b1000001010011100100010001011111010011100100010101000111 3
b1000000000000000 1
b1000000000000000 %
b1000000000000000 *
b1111 )
#16000
0#
b110100 "
b110100 .
b100000101001110010001000101111101001101010000010101001101001011 3
00
b110100 1
b11111111 '
b11111111 ,
b1001000110100 %
b1001000110100 *
b10000 )
#17000
1!
b0 "
b0 .
b1001110010011110101000001011111010100100100111001000100 3
12
b0 1
b101011001111000 '
b101011001111000 ,
b11 &
b11 +
b10001 )
#18000
b100111001001111010100000101111101001111010011100100010101010011 3
b1111111111111111 '
b1111111111111111 ,
b1111111111111111 %
b1111111111111111 *
b10010 )
#19000
b100111001001111010100000101111101011010010001010101001001001111 3
b0 '
b0 ,
b0 %
b0 *
b10011 )
#20000
b10100 )
